midd_media/__init__.py
midd_media/middimage.py
midd_media/middsound.py
midd_media-0.1.1.dist-info/METADATA
midd_media-0.1.1.dist-info/WHEEL
midd_media-0.1.1.dist-info/RECORD
